steamboat/__init__.py
steamboat/benchmarks.py
steamboat/dataset.py
steamboat/model.py
steamboat/tools.py
steamboat/utils.py
steamboat_bio-0.1.2.dist-info/licenses/LICENSE
steamboat_bio-0.1.2.dist-info/METADATA
steamboat_bio-0.1.2.dist-info/WHEEL
steamboat_bio-0.1.2.dist-info/top_level.txt
steamboat_bio-0.1.2.dist-info/RECORD
