Metadata-Version: 2.4
Name: steamboat-bio
Version: 0.1.2
Author-email: Shaoheng Liang <contact@using.issues>, Shaoheng Liang <author@example.com>, Jian Ma <author@example.com>
Project-URL: Homepage, https://github.com/ma-compbio/Steamboat
Project-URL: Issues, https://github.com/ma-compbio/Steamboat/issues
Classifier: Programming Language :: Python :: 3
Classifier: License :: OSI Approved :: MIT License
Classifier: Operating System :: OS Independent
Requires-Python: >=3.8
License-File: LICENSE
Requires-Dist: scanpy
Requires-Dist: squidpy
Requires-Dist: scipy
Requires-Dist: torch
Requires-Dist: networkx
Requires-Dist: igraph
Requires-Dist: leidenalg
Requires-Dist: matplotlib
Requires-Dist: scikit-learn
Requires-Dist: seaborn
Requires-Dist: tqdm
Dynamic: license-file
